topsis/__init__.py
topsis/__main__.py
topsis/tops.py
topsis_aashish_102017138-2.0.1.dist-info/LICENSE
topsis_aashish_102017138-2.0.1.dist-info/METADATA
topsis_aashish_102017138-2.0.1.dist-info/WHEEL
topsis_aashish_102017138-2.0.1.dist-info/entry_points.txt
topsis_aashish_102017138-2.0.1.dist-info/top_level.txt
topsis_aashish_102017138-2.0.1.dist-info/RECORD
