Metadata-Version: 2.1
Name: topsis-aashish-102017138
Version: 2.0.1
Summary: This is a Python library for handling problems related to Multiple Criteria Decision Making(MCDM) using TOPSIS algorithm
Home-page: https://github.com/aashish-1904
Author: Aashish Kumar
Author-email: aashishkumar19042002@gmail.com
License: MIT
Classifier: License :: OSI Approved :: MIT License
Classifier: Programming Language :: Python :: 3.6
Classifier: Programming Language :: Python :: 3.7
Classifier: Programming Language :: Python :: 3.8
License-File: LICENSE
Requires-Dist: numpy
Requires-Dist: pandas
